Metadata-Version: 2.1
Name: nginx-amplify-agent-health-check
Version: 0.1.6
Summary: Static and Dynamic Analysis for nginx-amplify-agent Health Status
Home-page: https://github.com/hiradyazdan/nginx-amplify-agent-health-check
Author: Hirad Yazdanpanah
Author-email: hirad.y@gmail.com
License: MIT
Keywords: nginx amplify nginx-amplify nginx-configuration health-check metrics
Platform: linux
Classifier: License :: OSI Approved :: MIT License
Classifier: Operating System :: POSIX
Classifier: Programming Language :: Python :: 2.7
Requires-Python: ==2.7.*
Provides-Extra: test
